imdb_rating_classifier/__init__.py
imdb_rating_classifier/generate.py
imdb_rating_classifier/penalizer.py
imdb_rating_classifier/schema.py
imdb_rating_classifier/scraper.py
imdb_rating_classifier/util/__init__.py
imdb_rating_classifier/util/unpack.py
imdb_rating_classifier-0.1.6.dist-info/LICENSE
imdb_rating_classifier-0.1.6.dist-info/METADATA
imdb_rating_classifier-0.1.6.dist-info/WHEEL
imdb_rating_classifier-0.1.6.dist-info/entry_points.txt
imdb_rating_classifier-0.1.6.dist-info/top_level.txt
imdb_rating_classifier-0.1.6.dist-info/RECORD
