Metadata-Version: 2.1
Name: imdb-rating-classifier
Version: 0.1.6
Summary: An application that scrapes data from IMDB and adjusts rating based on some rulesets.
Home-page: https://github.com/marouenes/imdb-rating-classifier
Author: Marouane Skandaji
Author-email: marouane.skandaji@gmail.com
License: MIT
Project-URL: Source Code, https://github.com/marouenes/imdb-rating-classifier
Project-URL: Bug Tracker, https://github.com/marouenes/imdb-rating-classifier/issues
Classifier: Intended Audience :: Developers
Classifier: License :: OSI Approved :: MIT License
Classifier: Programming Language :: Python :: 3
Classifier: Programming Language :: Python :: 3 :: Only
Classifier: Programming Language :: Python :: Implementation :: CPython
Requires-Python: >=3.8
License-File: LICENSE
Requires-Dist: Jinja2 (>=3.1.2)
Requires-Dist: beautifulsoup4 (>=4.10.0)
Requires-Dist: click (==8.1.3)
Requires-Dist: pandas (==1.5.2)
Requires-Dist: requests (>=2.28.1)
Provides-Extra: build
Requires-Dist: build ; extra == 'build'
Requires-Dist: twine ; extra == 'build'
Requires-Dist: wheel ; extra == 'build'
Provides-Extra: dev
Requires-Dist: black ; extra == 'dev'
Requires-Dist: build ; extra == 'dev'
Requires-Dist: flake8 ; extra == 'dev'
Requires-Dist: isort ; extra == 'dev'
Requires-Dist: pre-commit ; extra == 'dev'
Requires-Dist: pytest ; extra == 'dev'
Requires-Dist: pytest-cov ; extra == 'dev'
Requires-Dist: pytest-mock ; extra == 'dev'
Requires-Dist: twine ; extra == 'dev'
Requires-Dist: wheel ; extra == 'dev'
Provides-Extra: qa
Requires-Dist: black ; extra == 'qa'
Requires-Dist: flake8 ; extra == 'qa'
Requires-Dist: isort ; extra == 'qa'
Requires-Dist: pre-commit ; extra == 'qa'
Provides-Extra: tests
Requires-Dist: pytest ; extra == 'tests'
Requires-Dist: pytest-cov ; extra == 'tests'
Requires-Dist: pytest-mock ; extra == 'tests'
